woods.cp37-win_amd64.pyd
woods-0.1.0.dist-info/LICENSE
woods-0.1.0.dist-info/METADATA
woods-0.1.0.dist-info/WHEEL
woods-0.1.0.dist-info/top_level.txt
woods-0.1.0.dist-info/RECORD
