Metadata-Version: 2.1
Name: woods
Version: 0.1.0
Summary: Decision Trees Ensembles
Home-page: UNKNOWN
Author: UNKNOWN
Author-email: UNKNOWN
License: UNKNOWN
Platform: UNKNOWN
Requires-Dist: numpy
